bigquery_mcp/__init__.py
bigquery_mcp/config.py
bigquery_mcp/main.py
bigquery_mcp/server.py
sl_bigquery_mcp-0.1.8.dist-info/licenses/LICENSE
sl_bigquery_mcp-0.1.8.dist-info/METADATA
sl_bigquery_mcp-0.1.8.dist-info/WHEEL
sl_bigquery_mcp-0.1.8.dist-info/entry_points.txt
sl_bigquery_mcp-0.1.8.dist-info/top_level.txt
sl_bigquery_mcp-0.1.8.dist-info/RECORD
