Metadata-Version: 2.4
Name: sl-bigquery-mcp
Version: 0.1.8
Summary: A Model Context Protocol (MCP) server that provides access to BigQuery.
License-Expression: MIT
Project-URL: Homepage, https://www.snowleopard.ai
Project-URL: Repository, https://github.com/SnowLeopard-AI/bigquery-mcp?tab=readme-ov-file#readme
Project-URL: Issues, https://github.com/SnowLeopard-AI/bigquery-mcp/issues
Project-URL: Changelog, https://github.com/SnowLeopard-AI/bigquery-mcp/releases
Requires-Python: >=3.10
License-File: LICENSE
Requires-Dist: fastmcp==2.5.2
Requires-Dist: google-cloud-bigquery>=3.33.0
Requires-Dist: typer>=0.16.0
Dynamic: license-file
